{
    "avg": {
        "wmc": 6.71,
        "ccn": 4.04,
        "bugs": 0.12,
        "kanDefect": 0.43,
        "relativeSystemComplexity": 52.06,
        "relativeDataComplexity": 1.48,
        "relativeStructuralComplexity": 50.58,
        "volume": 356.92,
        "commentWeight": 38.79,
        "intelligentContent": 49.35,
        "lcom": 1.54,
        "instability": 0.6,
        "afferentCoupling": 0.92,
        "efferentCoupling": 2.33,
        "difficulty": 5.66,
        "mi": 99,
        "distance": 0.31,
        "incomingCDep": 1.67,
        "incomingPDep": 0.83,
        "outgoingCDep": 3.5,
        "outgoingPDep": 2.5,
        "classesPerPackage": 4
    },
    "sum": {
        "loc": 1697,
        "cloc": 687,
        "lloc": 1012,
        "nbMethods": 88,
        "nbClasses": 24,
        "nbInterfaces": 0,
        "nbPackages": 6,
        "violations": {
            "total": 6,
            "information": 0,
            "warning": 5,
            "error": 1,
            "critical": 0
        }
    }
}